odoo/addons/shopinvader_sale_packaging/README.rst
odoo/addons/shopinvader_sale_packaging/__init__.py
odoo/addons/shopinvader_sale_packaging/__manifest__.py
odoo/addons/shopinvader_sale_packaging/data/ir_export_product.xml
odoo/addons/shopinvader_sale_packaging/i18n/shopinvader_sale_packaging.pot
odoo/addons/shopinvader_sale_packaging/models/__init__.py
odoo/addons/shopinvader_sale_packaging/models/product_packaging.py
odoo/addons/shopinvader_sale_packaging/models/product_packaging_type.py
odoo/addons/shopinvader_sale_packaging/models/shopinvader_variant.py
odoo/addons/shopinvader_sale_packaging/readme/CONTRIBUTORS.rst
odoo/addons/shopinvader_sale_packaging/readme/CREDITS.rst
odoo/addons/shopinvader_sale_packaging/readme/DESCRIPTION.rst
odoo/addons/shopinvader_sale_packaging/services/__init__.py
odoo/addons/shopinvader_sale_packaging/services/abstract_sale.py
odoo/addons/shopinvader_sale_packaging/services/cart.py
odoo/addons/shopinvader_sale_packaging/services/packaging_mixin.py
odoo/addons/shopinvader_sale_packaging/static/description/index.html
odoo/addons/shopinvader_sale_packaging/tests/__init__.py
odoo/addons/shopinvader_sale_packaging/tests/test_cart.py
odoo/addons/shopinvader_sale_packaging/tests/test_product_data.py
odoo/addons/shopinvader_sale_packaging/tests/test_sale.py
odoo/addons/shopinvader_sale_packaging/views/product_packaging.xml
odoo/addons/shopinvader_sale_packaging/views/product_packaging_type.xml
odoo14_addon_shopinvader_sale_packaging-14.0.1.1.0.dist-info/METADATA
odoo14_addon_shopinvader_sale_packaging-14.0.1.1.0.dist-info/WHEEL
odoo14_addon_shopinvader_sale_packaging-14.0.1.1.0.dist-info/top_level.txt
odoo14_addon_shopinvader_sale_packaging-14.0.1.1.0.dist-info/RECORD
